{
  "name": "Associação Ferroviária de Esportes",
  "internalName": "ferroviaria",
  "shortName": "Ferroviária",
  "abbreviation": "AFE",
  "colors": {
    "outline": "#fafafc",
    "background": "#a44045",
    "name": "#fafafc"
  },
  "initialOverallStrength": 61,
  "players": [
    {
      "position": "GK",
      "name": "João Paulo"
    },
    {
      "position": "GK",
      "name": "Rafael Santos"
    },
    {
      "position": "DF",
      "name": "Bruno Silva"
    },
    {
      "position": "DF",
      "name": "Lucas Mendes"
    },
    {
      "position": "DF",
      "name": "Rafael Vaz"
    },
    {
      "position": "DF",
      "name": "Bruno Alves"
    },
    {
      "position": "DF",
      "name": "Lucas Rocha"
    },
    {
      "position": "DF",
      "name": "Rafael Costa"
    },
    {
      "position": "MF",
      "name": "Bruno Henrique"
    },
    {
      "position": "MF",
      "name": "Lucas Lima"
    },
    {
      "position": "MF",
      "name": "Rafael Silva"
    },
    {
      "position": "MF",
      "name": "Bruno César"
    },
    {
      "position": "MF",
      "name": "Lucas Moura"
    },
    {
      "position": "MF",
      "name": "Rafael Alves"
    },
    {
      "position": "MF",
      "name": "Bruno Santos"
    },
    {
      "position": "FW",
      "name": "Lucas Oliveira"
    },
    {
      "position": "FW",
      "name": "Rafael Martins"
    },
    {
      "position": "FW",
      "name": "Bruno Pereira"
    },
    {
      "position": "FW",
      "name": "Lucas Santos"
    },
    {
      "position": "FW",
      "name": "Rafael Lima"
    },
    {
      "position": "FW",
      "name": "Bruno Costa"
    },
    {
      "position": "FW",
      "name": "Lucas Almeida"
    },
    {
      "position": "FW",
      "name": "Rafael Silva"
    }
  ]
}
